odoo8_addon_project_categ-8.0.0.1.1-py2.7-nspkg.pth
odoo8_addon_project_categ-8.0.0.1.1.dist-info/top_level.txt
odoo8_addon_project_categ-8.0.0.1.1.dist-info/WHEEL
odoo8_addon_project_categ-8.0.0.1.1.dist-info/RECORD
odoo8_addon_project_categ-8.0.0.1.1.dist-info/metadata.json
odoo8_addon_project_categ-8.0.0.1.1.dist-info/DESCRIPTION.rst
odoo8_addon_project_categ-8.0.0.1.1.dist-info/METADATA
odoo8_addon_project_categ-8.0.0.1.1.dist-info/namespace_packages.txt
odoo_addons/project_categ/project_categ_view.xml
odoo_addons/project_categ/__openerp__.py
odoo_addons/project_categ/__init__.py
odoo_addons/project_categ/project_categ_model.py
odoo_addons/project_categ/i18n/ja.po
odoo_addons/project_categ/i18n/lv.po
odoo_addons/project_categ/i18n/zh_CN.po
odoo_addons/project_categ/i18n/uk.po
odoo_addons/project_categ/i18n/es_AR.po
odoo_addons/project_categ/i18n/el.po
odoo_addons/project_categ/i18n/ko.po
odoo_addons/project_categ/i18n/tr_TR.po
odoo_addons/project_categ/i18n/ru.po
odoo_addons/project_categ/i18n/pt.po
odoo_addons/project_categ/i18n/it.po
odoo_addons/project_categ/i18n/es_CL.po
odoo_addons/project_categ/i18n/es.po
odoo_addons/project_categ/i18n/nl_BE.po
odoo_addons/project_categ/i18n/ar.po
odoo_addons/project_categ/i18n/lt.po
odoo_addons/project_categ/i18n/ro.po
odoo_addons/project_categ/i18n/tr.po
odoo_addons/project_categ/i18n/sr.po
odoo_addons/project_categ/i18n/es_PY.po
odoo_addons/project_categ/i18n/mk.po
odoo_addons/project_categ/i18n/hr.po
odoo_addons/project_categ/i18n/bg.po
odoo_addons/project_categ/i18n/es_EC.po
odoo_addons/project_categ/i18n/zh_TW.po
odoo_addons/project_categ/i18n/hu.po
odoo_addons/project_categ/i18n/fr_CA.po
odoo_addons/project_categ/i18n/gl.po
odoo_addons/project_categ/i18n/ca.po
odoo_addons/project_categ/i18n/id.po
odoo_addons/project_categ/i18n/project_categ.pot
odoo_addons/project_categ/i18n/es_CR.po
odoo_addons/project_categ/i18n/he.po
odoo_addons/project_categ/i18n/es_CO.po
odoo_addons/project_categ/i18n/sl.po
odoo_addons/project_categ/i18n/sr@latin.po
odoo_addons/project_categ/i18n/th.po
odoo_addons/project_categ/i18n/es_PE.po
odoo_addons/project_categ/i18n/cs.po
odoo_addons/project_categ/i18n/pt_PT.po
odoo_addons/project_categ/i18n/nb.po
odoo_addons/project_categ/i18n/da.po
odoo_addons/project_categ/i18n/et.po
odoo_addons/project_categ/i18n/mn.po
